LICENSE
README.md
pyproject.toml
setup.py
MegaFlow2D.egg-info/PKG-INFO
MegaFlow2D.egg-info/SOURCES.txt
MegaFlow2D.egg-info/dependency_links.txt
MegaFlow2D.egg-info/requires.txt
MegaFlow2D.egg-info/top_level.txt
megaflow/__init__.py
megaflow/version.py
megaflow/common/__init__.py
megaflow/common/metrics.py
megaflow/common/utils.py
megaflow/dataset/MegaFlow2D.py
megaflow/dataset/__init__.py