Metadata-Version: 2.1
Name: MegaFlow2D
Version: 0.6.0
Summary: MegaFlow2D: A Large-Scale Dataset for 2D Flow Simulation
Home-page: https://github.com/cmudrc/MegaFlow2D
Author: Wenzhuo Xu, Noelia Grande Gutierrez and Christopher McComb
Author-email: wxu2@andrew.cmu.edu
License: MIT
Classifier: Topic :: Scientific/Engineering :: Artificial Intelligence
Classifier: Intended Audience :: Science/Research
Classifier: Programming Language :: Python :: 3
Classifier: License :: OSI Approved :: MIT License
Requires-Python: >=3.6
License-File: LICENSE
